pcc/__init__.py
pcc/pcc.py
pccdr-1.0.3.dist-info/licenses/LICENSE
pccdr-1.0.3.dist-info/METADATA
pccdr-1.0.3.dist-info/WHEEL
pccdr-1.0.3.dist-info/top_level.txt
pccdr-1.0.3.dist-info/RECORD
