Metadata-Version: 2.4
Name: pccdr
Version: 1.0.3
Summary: Dimensionality reduction by preserving clusters and correlations.
Home-page: https://github.com/jacobgil/pcc
Author: Jacob Gildenblat
Author-email: jacob.gildenblat@gmail.com
Project-URL: Bug Tracker, https://github.com/jacobgil/pcc/issues
Classifier: Programming Language :: Python :: 3
Classifier: License :: OSI Approved :: MIT License
Classifier: Operating System :: OS Independent
Requires-Python: >=3.8
License-File: LICENSE
Requires-Dist: torchdr>=0.2
Requires-Dist: numpy>=1.24
Requires-Dist: scikit-learn>=1.3.2
Dynamic: author
Dynamic: author-email
Dynamic: classifier
Dynamic: description
Dynamic: description-content-type
Dynamic: home-page
Dynamic: license-file
Dynamic: project-url
Dynamic: requires-dist
Dynamic: requires-python
Dynamic: summary
